ToolAgents/__init__.py
ToolAgents/function_tool.py
ToolAgents/mcp_tool.py
ToolAgents/agent_memory/__init__.py
ToolAgents/agent_memory/context_app_state.py
ToolAgents/agent_memory/semantic_memory/__init__.py
ToolAgents/agent_memory/semantic_memory/hdbscan_cluster_embeddings_strategy.py
ToolAgents/agent_memory/semantic_memory/memory.py
ToolAgents/agent_tools/__init__.py
ToolAgents/agent_tools/discord_tool.py
ToolAgents/agent_tools/file_tools.py
ToolAgents/agent_tools/git_tools.py
ToolAgents/agent_tools/github_tools.py
ToolAgents/agent_tools/web_search_tool.py
ToolAgents/agents/__init__.py
ToolAgents/agents/advanced_agent.py
ToolAgents/agents/base_llm_agent.py
ToolAgents/agents/chat_tool_agent.py
ToolAgents/agents/structured_output_agent.py
ToolAgents/knowledge/__init__.py
ToolAgents/knowledge/document/__init__.py
ToolAgents/knowledge/document/document.py
ToolAgents/knowledge/document/document_provider.py
ToolAgents/knowledge/document/implementations/__init__.py
ToolAgents/knowledge/document/implementations/pypdf2_pdf.py
ToolAgents/knowledge/document/implementations/pytesseract_pdf.py
ToolAgents/knowledge/text_processing/__init__.py
ToolAgents/knowledge/text_processing/summarizer.py
ToolAgents/knowledge/text_processing/text_processing_prompts.py
ToolAgents/knowledge/text_processing/text_splitter.py
ToolAgents/knowledge/text_processing/text_transformer.py
ToolAgents/knowledge/vector_database/__init__.py
ToolAgents/knowledge/vector_database/embedding_provider.py
ToolAgents/knowledge/vector_database/rag.py
ToolAgents/knowledge/vector_database/reranking_provider.py
ToolAgents/knowledge/vector_database/vector_database_provider.py
ToolAgents/knowledge/vector_database/implementations/__init__.py
ToolAgents/knowledge/vector_database/implementations/chroma_db.py
ToolAgents/knowledge/vector_database/implementations/mbxai_reranking.py
ToolAgents/knowledge/vector_database/implementations/sentence_transformer_embeddings.py
ToolAgents/knowledge/web_crawler/__init__.py
toolagents-0.2.9.dist-info/LICENSE
toolagents-0.2.9.dist-info/METADATA
toolagents-0.2.9.dist-info/WHEEL
toolagents-0.2.9.dist-info/top_level.txt
toolagents-0.2.9.dist-info/RECORD
