Metadata-Version: 2.2
Name: ToolAgents
Version: 0.2.9
Summary: ToolAgents is a lightweight and flexible framework for creating function-calling agents with various language models and APIs.
Author-email: Maximilian Winter <maximilian.winter.91@gmail.com>
Project-URL: Homepage, https://github.com/Maximilian-Winter/ToolAgents
Project-URL: Bug Tracker, https://github.com/Maximilian-Winter/ToolAgents/issues
Classifier: Programming Language :: Python :: 3
Classifier: License :: OSI Approved :: MIT License
Classifier: Operating System :: OS Independent
Requires-Python: >=3.10
License-File: LICENSE
Requires-Dist: pydantic>=2.5.3
Requires-Dist: requests>=2.31.0
Requires-Dist: pydantic-settings
Requires-Dist: docstring_parser
Requires-Dist: aiohttp
Requires-Dist: mistralai
Requires-Dist: mistral-common
Requires-Dist: openai
Requires-Dist: google-generativeai
Requires-Dist: anthropic
Requires-Dist: groq
Provides-Extra: additional-deps
Requires-Dist: sentence_transformers; extra == "additional-deps"
Requires-Dist: hdbscan; extra == "additional-deps"
Requires-Dist: transformers; extra == "additional-deps"
Requires-Dist: sentencepiece; extra == "additional-deps"
Requires-Dist: protobuf; extra == "additional-deps"
Requires-Dist: chromadb; extra == "additional-deps"
Requires-Dist: pdf2image; extra == "additional-deps"
Requires-Dist: pytesseract; extra == "additional-deps"
Requires-Dist: lxml_html_clean; extra == "additional-deps"
Provides-Extra: search
Requires-Dist: googlesearch-python; extra == "search"
Requires-Dist: markdownify; extra == "search"
Requires-Dist: camoufox; extra == "search"
